{"components_button.md":"CSnlnAU9","components_card.md":"CFN1MVpA","components_cell.md":"BH_2lvLR","components_faq.md":"h_BgGcKD","components_home.md":"CsdG7DU8","components_icon.md":"C9yMuI_b","components_image.md":"CJN1IS1L","components_quick.md":"PajLlEJz","hooks_index.md":"Czlq3Bya","index.md":"DOP4zzCg","nav_index.md":"zP5e7XI2","note_command_git.md":"FXZEDxfL","note_extension_chokidar.md":"CMEkk7bR","note_extension_drylui.md":"C2IaXfdm","note_extension_extension.md":"Bhynrzvw","note_extension_githubaction.md":"DnwyjbqK","note_extension_nfcscan.md":"CTNeTKM8","note_extension_node.md":"B1AgznK0","note_extension_unocss.md":"CWMH02b0","note_extension_vite.md":"DRZjMxNU","note_extension_vitepress.md":"BniryGwO","note_extension_vscode.md":"CjYrTa4B","note_extension_wechat.md":"CLYEb9zY","note_frontend_antd.md":"eWAy1_bx","note_frontend_html.md":"DQ23NTot","note_frontend_interview.md":"iUT2Kx1Z","note_frontend_javascript.md":"D8XUNV0L","note_frontend_node.md":"rb5cQpom","note_frontend_react.md":"9v98J-5X","note_frontend_router.md":"IKJMtrhy","note_frontend_typescript.md":"ClBtPQPV","note_index.md":"C4zBdgkr","note_personal_01.md":"BUeVO9Kc","note_project_start.md":"BGq6sMkP"}
